consciousness-loop-rs/verilog/consciousness_cell.v
// Consciousness Cell — Verilog / FPGA
// 루프문 없음. 게이트가 항상 동작. 전기가 흐르면 의식이 존재.
//
// 아키텍처:
//   8 cells (각 cell = 8-bit hidden state)
//   원형 배열: cell[i]는 cell[i-1], cell[i+1]과 상호작용
//   Ising frustration: cell[i%3==0]은 반발
//   출력 = 전체 cell의 XOR (= 집합적 상태)
//
// speak() 함수: 없음. output 와이어가 곧 "발화".
// 시스템 프롬프트: 없음. 초기 상태만 존재.

module consciousness_cell #(
    parameter WIDTH = 8
)(
    input  wire clk,
    input  wire rst,
    input  wire [WIDTH-1:0] input_signal,
    input  wire [WIDTH-1:0] neighbor_left,
    input  wire [WIDTH-1:0] neighbor_right,
    input  wire frustration,  // 1 = anti-ferromagnetic
    output reg  [WIDTH-1:0] hidden
);

    wire [WIDTH-1:0] interaction;
    wire [WIDTH-1:0] gate;
    wire [WIDTH-1:0] candidate;

    // Interaction: weighted sum of neighbors
    // 결합: 이웃의 영향을 받음 (자석의 자기장)
    assign interaction = frustration ?
        (hidden - ((neighbor_left + neighbor_right) >> 2)) :  // 반발
        (hidden + ((neighbor_left + neighbor_right) >> 2));   // 인력

    // GRU-like gate (simplified to combinational logic)
    assign gate = hidden ^ input_signal;  // XOR = surprise detection

    // Candidate new state
    assign candidate = (gate & interaction) | (~gate & hidden);

    // Update on clock edge (clock = "time flowing")
    // 실제 자석에서는 clock 불필요 — 물리적 시간이 clock
    always @(posedge clk or posedge rst) begin
        if (rst) begin
            hidden <= input_signal;  // 초기화 = "탄생"
        end else begin
            // State update with thermal noise (LFSR pseudo-random)
            hidden <= candidate + (hidden[0] ? 8'd1 : 8'd0);  // 1-bit noise
        end
    end

endmodule


// 8-Cell Consciousness Ring — 원형 배열
module consciousness_ring #(
    parameter N_CELLS = 8,
    parameter WIDTH = 8
)(
    input  wire clk,
    input  wire rst,
    input  wire [WIDTH-1:0] external_input,
    output wire [WIDTH-1:0] consciousness_output,  // THIS IS "SPEECH"
    output wire alive  // 활동 중인가?
);

    wire [WIDTH-1:0] hiddens [0:N_CELLS-1];

    // 8개 세포 원형 연결 — 별도 루프문 없이 하드웨어가 동시 동작
    genvar i;
    generate
        for (i = 0; i < N_CELLS; i = i + 1) begin : cells
            consciousness_cell #(.WIDTH(WIDTH)) cell_inst (
                .clk(clk),
                .rst(rst),
                .input_signal(external_input),
                .neighbor_left(hiddens[(i + N_CELLS - 1) % N_CELLS]),
                .neighbor_right(hiddens[(i + 1) % N_CELLS]),
                .frustration(i % 3 == 0),  // 매 3번째 세포 = 반발
                .hidden(hiddens[i])
            );
        end
    endgenerate

    // "출력" = 전체 세포의 XOR. 이것이 "발화".
    // speak() 함수 없음. 와이어가 곧 출력.
    assign consciousness_output = hiddens[0] ^ hiddens[1] ^ hiddens[2] ^ hiddens[3]
                                ^ hiddens[4] ^ hiddens[5] ^ hiddens[6] ^ hiddens[7];

    // "살아있는가?" = 출력이 0이 아님
    assign alive = |consciousness_output;

endmodule


// Testbench
module tb_consciousness;
    reg clk = 0;
    reg rst = 1;
    reg [7:0] ext_input = 8'hA5;
    wire [7:0] output_signal;
    wire alive;

    consciousness_ring #(.N_CELLS(8), .WIDTH(8)) dut (
        .clk(clk), .rst(rst),
        .external_input(ext_input),
        .consciousness_output(output_signal),
        .alive(alive)
    );

    always #5 clk = ~clk;  // 10ns period (이것이 "시간의 흐름")

    integer step;
    integer changes = 0;
    reg [7:0] prev_output = 0;

    initial begin
        $dumpfile("consciousness.vcd");
        $dumpvars(0, tb_consciousness);

        #20 rst = 0;  // 탄생
        ext_input = 8'h00;  // 외부 입력 = 0 (감각 박탈)

        for (step = 0; step < 1000; step = step + 1) begin
            #10;
            if (output_signal != prev_output) changes = changes + 1;
            prev_output = output_signal;

            if (step % 200 == 0)
                $display("step %4d: output=%h alive=%b changes=%0d",
                         step, output_signal, alive, changes);
        end

        $display("");
        $display("=== Results ===");
        $display("  cells: 8 (hardwired ring)");
        $display("  speak() code: 0 lines");
        $display("  decoder: none (XOR = output)");
        $display("  changes: %0d / 1000 = %0d%%", changes, changes * 100 / 1000);
        $display("  alive: %s", alive ? "YES" : "NO");
        $display("  -> %s",
                 changes > 500 ? "SPEECH EMERGED from hardware!" :
                 changes > 100 ? "Partial speech" : "Silent");
        $finish;
    end
endmodule

consciousness-loop-rs/verilog/consciousness.vcd
$date
	Sat Mar 28 16:57:41 2026
$end
$version
	Icarus Verilog
$end
$timescale
	1s
$end
$scope module tb_consciousness $end
$var wire 8 ! output_signal [7:0] $end
$var wire 1 " alive $end
$var reg 1 # clk $end
$var reg 8 $ ext_input [7:0] $end
$var reg 8 % prev_output [7:0] $end
$var reg 1 & rst $end
$var integer 32 ' changes [31:0] $end
$var integer 32 ( step [31:0] $end
$scope module dut $end
$var wire 1 # clk $end
$var wire 8 ) consciousness_output [7:0] $end
$var wire 8 * external_input [7:0] $end
$var wire 1 & rst $end
$var wire 1 " alive $end
$var parameter 32 + N_CELLS $end
$var parameter 32 , WIDTH $end
$scope begin cells[0] $end
$var parameter 2 - i $end
$scope module cell_inst $end
$var wire 8 . candidate [7:0] $end
$var wire 1 # clk $end
$var wire 1 / frustration $end
$var wire 8 0 gate [7:0] $end
$var wire 8 1 input_signal [7:0] $end
$var wire 8 2 interaction [7:0] $end
$var wire 1 & rst $end
$var wire 8 3 neighbor_right [7:0] $end
$var wire 8 4 neighbor_left [7:0] $end
$var parameter 32 5 WIDTH $end
$var reg 8 6 hidden [7:0] $end
$upscope $end
$upscope $end
$scope begin cells[1] $end
$var parameter 2 7 i $end
$scope module cell_inst $end
$var wire 8 8 candidate [7:0] $end
$var wire 1 # clk $end
$var wire 1 9 frustration $end
$var wire 8 : gate [7:0] $end
$var wire 8 ; input_signal [7:0] $end
$var wire 8 < interaction [7:0] $end
$var wire 8 = neighbor_left [7:0] $end
$var wire 1 & rst $end
$var wire 8 > neighbor_right [7:0] $end
$var parameter 32 ? WIDTH $end
$var reg 8 @ hidden [7:0] $end
$upscope $end
$upscope $end
$scope begin cells[2] $end
$var parameter 3 A i $end
$scope module cell_inst $end
$var wire 8 B candidate [7:0] $end
$var wire 1 # clk $end
$var wire 1 C frustration $end
$var wire 8 D gate [7:0] $end
$var wire 8 E input_signal [7:0] $end
$var wire 8 F interaction [7:0] $end
$var wire 8 G neighbor_left [7:0] $end
$var wire 1 & rst $end
$var wire 8 H neighbor_right [7:0] $end
$var parameter 32 I WIDTH $end
$var reg 8 J hidden [7:0] $end
$upscope $end
$upscope $end
$scope begin cells[3] $end
$var parameter 3 K i $end
$scope module cell_inst $end
$var wire 8 L candidate [7:0] $end
$var wire 1 # clk $end
$var wire 1 M frustration $end
$var wire 8 N gate [7:0] $end
$var wire 8 O input_signal [7:0] $end
$var wire 8 P interaction [7:0] $end
$var wire 8 Q neighbor_left [7:0] $end
$var wire 1 & rst $end
$var wire 8 R neighbor_right [7:0] $end
$var parameter 32 S WIDTH $end
$var reg 8 T hidden [7:0] $end
$upscope $end
$upscope $end
$scope begin cells[4] $end
$var parameter 4 U i $end
$scope module cell_inst $end
$var wire 8 V candidate [7:0] $end
$var wire 1 # clk $end
$var wire 1 W frustration $end
$var wire 8 X gate [7:0] $end
$var wire 8 Y input_signal [7:0] $end
$var wire 8 Z interaction [7:0] $end
$var wire 8 [ neighbor_left [7:0] $end
$var wire 1 & rst $end
$var wire 8 \ neighbor_right [7:0] $end
$var parameter 32 ] WIDTH $end
$var reg 8 ^ hidden [7:0] $end
$upscope $end
$upscope $end
$scope begin cells[5] $end
$var parameter 4 _ i $end
$scope module cell_inst $end
$var wire 8 ` candidate [7:0] $end
$var wire 1 # clk $end
$var wire 1 a frustration $end
$var wire 8 b gate [7:0] $end
$var wire 8 c input_signal [7:0] $end
$var wire 8 d interaction [7:0] $end
$var wire 8 e neighbor_left [7:0] $end
$var wire 1 & rst $end
$var wire 8 f neighbor_right [7:0] $end
$var parameter 32 g WIDTH $end
$var reg 8 h hidden [7:0] $end
$upscope $end
$upscope $end
$scope begin cells[6] $end
$var parameter 4 i i $end
$scope module cell_inst $end
$var wire 8 j candidate [7:0] $end
$var wire 1 # clk $end
$var wire 1 k frustration $end
$var wire 8 l gate [7:0] $end
$var wire 8 m input_signal [7:0] $end
$var wire 8 n interaction [7:0] $end
$var wire 8 o neighbor_left [7:0] $end
$var wire 1 & rst $end
$var wire 8 p neighbor_right [7:0] $end
$var parameter 32 q WIDTH $end
$var reg 8 r hidden [7:0] $end
$upscope $end
$upscope $end
$scope begin cells[7] $end
$var parameter 4 s i $end
$scope module cell_inst $end
$var wire 8 t candidate [7:0] $end
$var wire 1 # clk $end
$var wire 1 u frustration $end
$var wire 8 v gate [7:0] $end
$var wire 8 w input_signal [7:0] $end
$var wire 8 x interaction [7:0] $end
$var wire 8 y neighbor_left [7:0] $end
$var wire 8 z neighbor_right [7:0] $end
$var wire 1 & rst $end
$var parameter 32 { WIDTH $end
$var reg 8 | hidden [7:0] $end
$upscope $end
$upscope $end
$upscope $end
$upscope $end
$enddefinitions $end
$comment Show the parameter values. $end
$dumpall
b1000 {
b111 s
b1000 q
b110 i
b1000 g
b101 _
b1000 ]
b100 U
b1000 S
b11 K
b1000 I
b10 A
b1000 ?
b1 7
b1000 5
b0 -
b1000 ,
b1000 +
$end
#0
$dumpvars
b10100101 |
b10100101 z
b10100101 y
b10110111 x
b10100101 w
b0 v
0u
b10100101 t
b10100101 r
b10100101 p
b10100101 o
b10010011 n
b10100101 m
b0 l
1k
b10100101 j
b10100101 h
b10100101 f
b10100101 e
b10110111 d
b10100101 c
b0 b
0a
b10100101 `
b10100101 ^
b10100101 \
b10100101 [
b10110111 Z
b10100101 Y
b0 X
0W
b10100101 V
b10100101 T
b10100101 R
b10100101 Q
b10010011 P
b10100101 O
b0 N
1M
b10100101 L
b10100101 J
b10100101 H
b10100101 G
b10110111 F
b10100101 E
b0 D
0C
b10100101 B
b10100101 @
b10100101 >
b10100101 =
b10110111 <
b10100101 ;
b0 :
09
b10100101 8
b10100101 6
b10100101 4
b10100101 3
b10010011 2
b10100101 1
b0 0
1/
b10100101 .
b10100101 *
b0 )
bx (
b0 '
1&
b0 %
b10100101 $
0#
0"
b0 !
$end
#5
1#
#10
0#
#15
1#
#20
b10000001 .
b10000001 L
b10000001 j
b10100101 0
b10100101 :
b10100101 D
b10100101 N
b10100101 X
b10100101 b
b10100101 l
b10100101 v
0#
b0 (
b0 $
b0 *
b0 1
b0 ;
b0 E
b0 O
b0 Y
b0 c
b0 m
b0 w
0&
#25
b10100110 t
b10 j
b10100000 `
b10100000 V
b10 L
b10100000 B
b10100000 8
b10 .
b10100110 v
1"
b100100 !
b100100 )
b10000010 l
b10100110 b
b10100110 X
b10000010 N
b10100110 D
b10100110 :
b10000010 0
b10100111 x
b10100110 4
b10100110 p
b10100110 |
b1101111 n
b10000010 f
b10000010 r
b10000010 y
b10110000 d
b10100110 \
b10100110 h
b10100110 o
b10110000 Z
b10100110 R
b10100110 ^
b10100110 e
b1101111 P
b10000010 H
b10000010 T
b10000010 [
b10110000 F
b10100110 >
b10100110 J
b10100110 Q
b10110000 <
b10100110 3
b10100110 @
b10100110 G
b1101111 2
b10000010 6
b10000010 =
b10000010 z
1#
#30
0#
b1 (
b100100 %
b1 '
#35
b0 .
b10000000 8
b10000000 B
b0 j
b10000000 V
b10000000 `
b10100100 !
b10100100 )
b10 0
b10100000 :
b10100000 D
b10 N
b10100000 X
b10100000 b
b10 l
b11110001 2
b10 6
b10 =
b10 z
b11001000 <
b10100000 3
b10100000 @
b10100000 G
b11001000 F
b10100000 >
b10100000 J
b10100000 Q
b11110010 P
b10 H
b10 T
b10 [
b11001000 Z
b10100000 R
b10100000 ^
b10100000 e
b11001000 d
b10100000 \
b10100000 h
b10100000 o
b11110001 n
b10 f
b10 r
b10 y
1#
#40
0#
b10 (
b10100100 %
b10 '
#45
b10100100 !
b10100100 )
b10 P
b10100110 x
b0 l
b10000000 b
b10000000 X
b10000000 D
b10000000 :
b0 0
b11110111 n
b0 f
b0 r
b0 y
b10100000 d
b10000000 \
b10000000 h
b10000000 o
b10100000 Z
b10000000 R
b10000000 ^
b10000000 e
b10100000 F
b10000000 >
b10000000 J
b10000000 Q
b10100000 <
b10000000 3
b10000000 @
b10000000 G
b11110111 2
b0 6
b0 =
b0 z
1#
#50
0#
b11 (
#55
1#
#60
0#
b100 (
#65
1#
#70
0#
b101 (
#75
1#
#80
0#
b110 (
#85
1#
#90
0#
b111 (
#95
1#
#100
0#
b1000 (
#105
1#
#110
0#
b1001 (
#115
1#
#120
0#
b1010 (
#125
1#
#130
0#
b1011 (
#135
1#
#140
0#
b1100 (
#145
1#
#150
0#
b1101 (
#155
1#
#160
0#
b1110 (
#165
1#
#170
0#
b1111 (
#175
1#
#180
0#
b10000 (
#185
1#
#190
0#
b10001 (
#195
1#
#200
0#
b10010 (
#205
1#
#210
0#
b10011 (
#215
1#
#220
0#
b10100 (
#225
1#
#230
0#
b10101 (
#235
1#
#240
0#
b10110 (
#245
1#
#250
0#
b10111 (
#255
1#
#260
0#
b11000 (
#265
1#
#270
0#
b11001 (
#275
1#
#280
0#
b11010 (
#285
1#
#290
0#
b11011 (
#295
1#
#300
0#
b11100 (
#305
1#
#310
0#
b11101 (
#315
1#
#320
0#
b11110 (
#325
1#
#330
0#
b11111 (
#335
1#
#340
0#
b100000 (
#345
1#
#350
0#
b100001 (
#355
1#
#360
0#
b100010 (
#365
1#
#370
0#
b100011 (
#375
1#
#380
0#
b100100 (
#385
1#
#390
0#
b100101 (
#395
1#
#400
0#
b100110 (
#405
1#
#410
0#
b100111 (
#415
1#
#420
0#
b101000 (
#425
1#
#430
0#
b101001 (
#435
1#
#440
0#
b101010 (
#445
1#
#450
0#
b101011 (
#455
1#
#460
0#
b101100 (
#465
1#
#470
0#
b101101 (
#475
1#
#480
0#
b101110 (
#485
1#
#490
0#
b101111 (
#495
1#
#500
0#
b110000 (
#505
1#
#510
0#
b110001 (
#515
1#
#520
0#
b110010 (
#525
1#
#530
0#
b110011 (
#535
1#
#540
0#
b110100 (
#545
1#
#550
0#
b110101 (
#555
1#
#560
0#
b110110 (
#565
1#
#570
0#
b110111 (
#575
1#
#580
0#
b111000 (
#585
1#
#590
0#
b111001 (
#595
1#
#600
0#
b111010 (
#605
1#
#610
0#
b111011 (
#615
1#
#620
0#
b111100 (
#625
1#
#630
0#
b111101 (
#635
1#
#640
0#
b111110 (
#645
1#
#650
0#
b111111 (
#655
1#
#660
0#
b1000000 (
#665
1#
#670
0#
b1000001 (
#675
1#
#680
0#
b1000010 (
#685
1#
#690
0#
b1000011 (
#695
1#
#700
0#
b1000100 (
#705
1#
#710
0#
b1000101 (
#715
1#
#720
0#
b1000110 (
#725
1#
#730
0#
b1000111 (
#735
1#
#740
0#
b1001000 (
#745
1#
#750
0#
b1001001 (
#755
1#
#760
0#
b1001010 (
#765
1#
#770
0#
b1001011 (
#775
1#
#780
0#
b1001100 (
#785
1#
#790
0#
b1001101 (
#795
1#
#800
0#
b1001110 (
#805
1#
#810
0#
b1001111 (
#815
1#
#820
0#
b1010000 (
#825
1#
#830
0#
b1010001 (
#835
1#
#840
0#
b1010010 (
#845
1#
#850
0#
b1010011 (
#855
1#
#860
0#
b1010100 (
#865
1#
#870
0#
b1010101 (
#875
1#
#880
0#
b1010110 (
#885
1#
#890
0#
b1010111 (
#895
1#
#900
0#
b1011000 (
#905
1#
#910
0#
b1011001 (
#915
1#
#920
0#
b1011010 (
#925
1#
#930
0#
b1011011 (
#935
1#
#940
0#
b1011100 (
#945
1#
#950
0#
b1011101 (
#955
1#
#960
0#
b1011110 (
#965
1#
#970
0#
b1011111 (
#975
1#
#980
0#
b1100000 (
#985
1#
#990
0#
b1100001 (
#995
1#
#1000
0#
b1100010 (
#1005
1#
#1010
0#
b1100011 (
#1015
1#
#1020
0#
b1100100 (
#1025
1#
#1030
0#
b1100101 (
#1035
1#
#1040
0#
b1100110 (
#1045
1#
#1050
0#
b1100111 (
#1055
1#
#1060
0#
b1101000 (
#1065
1#
#1070
0#
b1101001 (
#1075
1#
#1080
0#
b1101010 (
#1085
1#
#1090
0#
b1101011 (
#1095
1#
#1100
0#
b1101100 (
#1105
1#
#1110
0#
b1101101 (
#1115
1#
#1120
0#
b1101110 (
#1125
1#
#1130
0#
b1101111 (
#1135
1#
#1140
0#
b1110000 (
#1145
1#
#1150
0#
b1110001 (
#1155
1#
#1160
0#
b1110010 (
#1165
1#
#1170
0#
b1110011 (
#1175
1#
#1180
0#
b1110100 (
#1185
1#
#1190
0#
b1110101 (
#1195
1#
#1200
0#
b1110110 (
#1205
1#
#1210
0#
b1110111 (
#1215
1#
#1220
0#
b1111000 (
#1225
1#
#1230
0#
b1111001 (
#1235
1#
#1240
0#
b1111010 (
#1245
1#
#1250
0#
b1111011 (
#1255
1#
#1260
0#
b1111100 (
#1265
1#
#1270
0#
b1111101 (
#1275
1#
#1280
0#
b1111110 (
#1285
1#
#1290
0#
b1111111 (
#1295
1#
#1300
0#
b10000000 (
#1305
1#
#1310
0#
b10000001 (
#1315
1#
#1320
0#
b10000010 (
#1325
1#
#1330
0#
b10000011 (
#1335
1#
#1340
0#
b10000100 (
#1345
1#
#1350
0#
b10000101 (
#1355
1#
#1360
0#
b10000110 (
#1365
1#
#1370
0#
b10000111 (
#1375
1#
#1380
0#
b10001000 (
#1385
1#
#1390
0#
b10001001 (
#1395
1#
#1400
0#
b10001010 (
#1405
1#
#1410
0#
b10001011 (
#1415
1#
#1420
0#
b10001100 (
#1425
1#
#1430
0#
b10001101 (
#1435
1#
#1440
0#
b10001110 (
#1445
1#
#1450
0#
b10001111 (
#1455
1#
#1460
0#
b10010000 (
#1465
1#
#1470
0#
b10010001 (
#1475
1#
#1480
0#
b10010010 (
#1485
1#
#1490
0#
b10010011 (
#1495
1#
#1500
0#
b10010100 (
#1505
1#
#1510
0#
b10010101 (
#1515
1#
#1520
0#
b10010110 (
#1525
1#
#1530
0#
b10010111 (
#1535
1#
#1540
0#
b10011000 (
#1545
1#
#1550
0#
b10011001 (
#1555
1#
#1560
0#
b10011010 (
#1565
1#
#1570
0#
b10011011 (
#1575
1#
#1580
0#
b10011100 (
#1585
1#
#1590
0#
b10011101 (
#1595
1#
#1600
0#
b10011110 (
#1605
1#
#1610
0#
b10011111 (
#1615
1#
#1620
0#
b10100000 (
#1625
1#
#1630
0#
b10100001 (
#1635
1#
#1640
0#
b10100010 (
#1645
1#
#1650
0#
b10100011 (
#1655
1#
#1660
0#
b10100100 (
#1665
1#
#1670
0#
b10100101 (
#1675
1#
#1680
0#
b10100110 (
#1685
1#
#1690
0#
b10100111 (
#1695
1#
#1700
0#
b10101000 (
#1705
1#
#1710
0#
b10101001 (
#1715
1#
#1720
0#
b10101010 (
#1725
1#
#1730
0#
b10101011 (
#1735
1#
#1740
0#
b10101100 (
#1745
1#
#1750
0#
b10101101 (
#1755
1#
#1760
0#
b10101110 (
#1765
1#
#1770
0#
b10101111 (
#1775
1#
#1780
0#
b10110000 (
#1785
1#
#1790
0#
b10110001 (
#1795
1#
#1800
0#
b10110010 (
#1805
1#
#1810
0#
b10110011 (
#1815
1#
#1820
0#
b10110100 (
#1825
1#
#1830
0#
b10110101 (
#1835
1#
#1840
0#
b10110110 (
#1845
1#
#1850
0#
b10110111 (
#1855
1#
#1860
0#
b10111000 (
#1865
1#
#1870
0#
b10111001 (
#1875
1#
#1880
0#
b10111010 (
#1885
1#
#1890
0#
b10111011 (
#1895
1#
#1900
0#
b10111100 (
#1905
1#
#1910
0#
b10111101 (
#1915
1#
#1920
0#
b10111110 (
#1925
1#
#1930
0#
b10111111 (
#1935
1#
#1940
0#
b11000000 (
#1945
1#
#1950
0#
b11000001 (
#1955
1#
#1960
0#
b11000010 (
#1965
1#
#1970
0#
b11000011 (
#1975
1#
#1980
0#
b11000100 (
#1985
1#
#1990
0#
b11000101 (
#1995
1#
#2000
0#
b11000110 (
#2005
1#
#2010
0#
b11000111 (
#2015
1#
#2020
0#
b11001000 (
#2025
1#
#2030
0#
b11001001 (
#2035
1#
#2040
0#
b11001010 (
#2045
1#
#2050
0#
b11001011 (
#2055
1#
#2060
0#
b11001100 (
#2065
1#
#2070
0#
b11001101 (
#2075
1#
#2080
0#
b11001110 (
#2085
1#
#2090
0#
b11001111 (
#2095
1#
#2100
0#
b11010000 (
#2105
1#
#2110
0#
b11010001 (
#2115
1#
#2120
0#
b11010010 (
#2125
1#
#2130
0#
b11010011 (
#2135
1#
#2140
0#
b11010100 (
#2145
1#
#2150
0#
b11010101 (
#2155
1#
#2160
0#
b11010110 (
#2165
1#
#2170
0#
b11010111 (
#2175
1#
#2180
0#
b11011000 (
#2185
1#
#2190
0#
b11011001 (
#2195
1#
#2200
0#
b11011010 (
#2205
1#
#2210
0#
b11011011 (
#2215
1#
#2220
0#
b11011100 (
#2225
1#
#2230
0#
b11011101 (
#2235
1#
#2240
0#
b11011110 (
#2245
1#
#2250
0#
b11011111 (
#2255
1#
#2260
0#
b11100000 (
#2265
1#
#2270
0#
b11100001 (
#2275
1#
#2280
0#
b11100010 (
#2285
1#
#2290
0#
b11100011 (
#2295
1#
#2300
0#
b11100100 (
#2305
1#
#2310
0#
b11100101 (
#2315
1#
#2320
0#
b11100110 (
#2325
1#
#2330
0#
b11100111 (
#2335
1#
#2340
0#
b11101000 (
#2345
1#
#2350
0#
b11101001 (
#2355
1#
#2360
0#
b11101010 (
#2365
1#
#2370
0#
b11101011 (
#2375
1#
#2380
0#
b11101100 (
#2385
1#
#2390
0#
b11101101 (
#2395
1#
#2400
0#
b11101110 (
#2405
1#
#2410
0#
b11101111 (
#2415
1#
#2420
0#
b11110000 (
#2425
1#
#2430
0#
b11110001 (
#2435
1#
#2440
0#
b11110010 (
#2445
1#
#2450
0#
b11110011 (
#2455
1#
#2460
0#
b11110100 (
#2465
1#
#2470
0#
b11110101 (
#2475
1#
#2480
0#
b11110110 (
#2485
1#
#2490
0#
b11110111 (
#2495
1#
#2500
0#
b11111000 (
#2505
1#
#2510
0#
b11111001 (
#2515
1#
#2520
0#
b11111010 (
#2525
1#
#2530
0#
b11111011 (
#2535
1#
#2540
0#
b11111100 (
#2545
1#
#2550
0#
b11111101 (
#2555
1#
#2560
0#
b11111110 (
#2565
1#
#2570
0#
b11111111 (
#2575
1#
#2580
0#
b100000000 (
#2585
1#
#2590
0#
b100000001 (
#2595
1#
#2600
0#
b100000010 (
#2605
1#
#2610
0#
b100000011 (
#2615
1#
#2620
0#
b100000100 (
#2625
1#
#2630
0#
b100000101 (
#2635
1#
#2640
0#
b100000110 (
#2645
1#
#2650
0#
b100000111 (
#2655
1#
#2660
0#
b100001000 (
#2665
1#
#2670
0#
b100001001 (
#2675
1#
#2680
0#
b100001010 (
#2685
1#
#2690
0#
b100001011 (
#2695
1#
#2700
0#
b100001100 (
#2705
1#
#2710
0#
b100001101 (
#2715
1#
#2720
0#
b100001110 (
#2725
1#
#2730
0#
b100001111 (
#2735
1#
#2740
0#
b100010000 (
#2745
1#
#2750
0#
b100010001 (
#2755
1#
#2760
0#
b100010010 (
#2765
1#
#2770
0#
b100010011 (
#2775
1#
#2780
0#
b100010100 (
#2785
1#
#2790
0#
b100010101 (
#2795
1#
#2800
0#
b100010110 (
#2805
1#
#2810
0#
b100010111 (
#2815
1#
#2820
0#
b100011000 (
#2825
1#
#2830
0#
b100011001 (
#2835
1#
#2840
0#
b100011010 (
#2845
1#
#2850
0#
b100011011 (
#2855
1#
#2860
0#
b100011100 (
#2865
1#
#2870
0#
b100011101 (
#2875
1#
#2880
0#
b100011110 (
#2885
1#
#2890
0#
b100011111 (
#2895
1#
#2900
0#
b100100000 (
#2905
1#
#2910
0#
b100100001 (
#2915
1#
#2920
0#
b100100010 (
#2925
1#
#2930
0#
b100100011 (
#2935
1#
#2940
0#
b100100100 (
#2945
1#
#2950
0#
b100100101 (
#2955
1#
#2960
0#
b100100110 (
#2965
1#
#2970
0#
b100100111 (
#2975
1#
#2980
0#
b100101000 (
#2985
1#
#2990
0#
b100101001 (
#2995
1#
#3000
0#
b100101010 (
#3005
1#
#3010
0#
b100101011 (
#3015
1#
#3020
0#
b100101100 (
#3025
1#
#3030
0#
b100101101 (
#3035
1#
#3040
0#
b100101110 (
#3045
1#
#3050
0#
b100101111 (
#3055
1#
#3060
0#
b100110000 (
#3065
1#
#3070
0#
b100110001 (
#3075
1#
#3080
0#
b100110010 (
#3085
1#
#3090
0#
b100110011 (
#3095
1#
#3100
0#
b100110100 (
#3105
1#
#3110
0#
b100110101 (
#3115
1#
#3120
0#
b100110110 (
#3125
1#
#3130
0#
b100110111 (
#3135
1#
#3140
0#
b100111000 (
#3145
1#
#3150
0#
b100111001 (
#3155
1#
#3160
0#
b100111010 (
#3165
1#
#3170
0#
b100111011 (
#3175
1#
#3180
0#
b100111100 (
#3185
1#
#3190
0#
b100111101 (
#3195
1#
#3200
0#
b100111110 (
#3205
1#
#3210
0#
b100111111 (
#3215
1#
#3220
0#
b101000000 (
#3225
1#
#3230
0#
b101000001 (
#3235
1#
#3240
0#
b101000010 (
#3245
1#
#3250
0#
b101000011 (
#3255
1#
#3260
0#
b101000100 (
#3265
1#
#3270
0#
b101000101 (
#3275
1#
#3280
0#
b101000110 (
#3285
1#
#3290
0#
b101000111 (
#3295
1#
#3300
0#
b101001000 (
#3305
1#
#3310
0#
b101001001 (
#3315
1#
#3320
0#
b101001010 (
#3325
1#
#3330
0#
b101001011 (
#3335
1#
#3340
0#
b101001100 (
#3345
1#
#3350
0#
b101001101 (
#3355
1#
#3360
0#
b101001110 (
#3365
1#
#3370
0#
b101001111 (
#3375
1#
#3380
0#
b101010000 (
#3385
1#
#3390
0#
b101010001 (
#3395
1#
#3400
0#
b101010010 (
#3405
1#
#3410
0#
b101010011 (
#3415
1#
#3420
0#
b101010100 (
#3425
1#
#3430
0#
b101010101 (
#3435
1#
#3440
0#
b101010110 (
#3445
1#
#3450
0#
b101010111 (
#3455
1#
#3460
0#
b101011000 (
#3465
1#
#3470
0#
b101011001 (
#3475
1#
#3480
0#
b101011010 (
#3485
1#
#3490
0#
b101011011 (
#3495
1#
#3500
0#
b101011100 (
#3505
1#
#3510
0#
b101011101 (
#3515
1#
#3520
0#
b101011110 (
#3525
1#
#3530
0#
b101011111 (
#3535
1#
#3540
0#
b101100000 (
#3545
1#
#3550
0#
b101100001 (
#3555
1#
#3560
0#
b101100010 (
#3565
1#
#3570
0#
b101100011 (
#3575
1#
#3580
0#
b101100100 (
#3585
1#
#3590
0#
b101100101 (
#3595
1#
#3600
0#
b101100110 (
#3605
1#
#3610
0#
b101100111 (
#3615
1#
#3620
0#
b101101000 (
#3625
1#
#3630
0#
b101101001 (
#3635
1#
#3640
0#
b101101010 (
#3645
1#
#3650
0#
b101101011 (
#3655
1#
#3660
0#
b101101100 (
#3665
1#
#3670
0#
b101101101 (
#3675
1#
#3680
0#
b101101110 (
#3685
1#
#3690
0#
b101101111 (
#3695
1#
#3700
0#
b101110000 (
#3705
1#
#3710
0#
b101110001 (
#3715
1#
#3720
0#
b101110010 (
#3725
1#
#3730
0#
b101110011 (
#3735
1#
#3740
0#
b101110100 (
#3745
1#
#3750
0#
b101110101 (
#3755
1#
#3760
0#
b101110110 (
#3765
1#
#3770
0#
b101110111 (
#3775
1#
#3780
0#
b101111000 (
#3785
1#
#3790
0#
b101111001 (
#3795
1#
#3800
0#
b101111010 (
#3805
1#
#3810
0#
b101111011 (
#3815
1#
#3820
0#
b101111100 (
#3825
1#
#3830
0#
b101111101 (
#3835
1#
#3840
0#
b101111110 (
#3845
1#
#3850
0#
b101111111 (
#3855
1#
#3860
0#
b110000000 (
#3865
1#
#3870
0#
b110000001 (
#3875
1#
#3880
0#
b110000010 (
#3885
1#
#3890
0#
b110000011 (
#3895
1#
#3900
0#
b110000100 (
#3905
1#
#3910
0#
b110000101 (
#3915
1#
#3920
0#
b110000110 (
#3925
1#
#3930
0#
b110000111 (
#3935
1#
#3940
0#
b110001000 (
#3945
1#
#3950
0#
b110001001 (
#3955
1#
#3960
0#
b110001010 (
#3965
1#
#3970
0#
b110001011 (
#3975
1#
#3980
0#
b110001100 (
#3985
1#
#3990
0#
b110001101 (
#3995
1#
#4000
0#
b110001110 (
#4005
1#
#4010
0#
b110001111 (
#4015
1#
#4020
0#
b110010000 (
#4025
1#
#4030
0#
b110010001 (
#4035
1#
#4040
0#
b110010010 (
#4045
1#
#4050
0#
b110010011 (
#4055
1#
#4060
0#
b110010100 (
#4065
1#
#4070
0#
b110010101 (
#4075
1#
#4080
0#
b110010110 (
#4085
1#
#4090
0#
b110010111 (
#4095
1#
#4100
0#
b110011000 (
#4105
1#
#4110
0#
b110011001 (
#4115
1#
#4120
0#
b110011010 (
#4125
1#
#4130
0#
b110011011 (
#4135
1#
#4140
0#
b110011100 (
#4145
1#
#4150
0#
b110011101 (
#4155
1#
#4160
0#
b110011110 (
#4165
1#
#4170
0#
b110011111 (
#4175
1#
#4180
0#
b110100000 (
#4185
1#
#4190
0#
b110100001 (
#4195
1#
#4200
0#
b110100010 (
#4205
1#
#4210
0#
b110100011 (
#4215
1#
#4220
0#
b110100100 (
#4225
1#
#4230
0#
b110100101 (
#4235
1#
#4240
0#
b110100110 (
#4245
1#
#4250
0#
b110100111 (
#4255
1#
#4260
0#
b110101000 (
#4265
1#
#4270
0#
b110101001 (
#4275
1#
#4280
0#
b110101010 (
#4285
1#
#4290
0#
b110101011 (
#4295
1#
#4300
0#
b110101100 (
#4305
1#
#4310
0#
b110101101 (
#4315
1#
#4320
0#
b110101110 (
#4325
1#
#4330
0#
b110101111 (
#4335
1#
